microbots/MicroBot.py
microbots/__init__.py
microbots/constants.py
microbots/bot/BrowsingBot.py
microbots/bot/LogAnalysisBot.py
microbots/bot/ReadingBot.py
microbots/bot/WritingBot.py
microbots/bot/__init__.py
microbots/environment/Environment.py
microbots/environment/local_docker/LocalDockerEnvironment.py
microbots/environment/local_docker/__init__.py
microbots/environment/local_docker/image_builder/Dockerfile
microbots/environment/local_docker/image_builder/ShellCommunicator.py
microbots/environment/local_docker/image_builder/dockerShell.py
microbots/environment/swe-rex/LocalDocker.py
microbots/extras/__init__.py
microbots/extras/mount.py
microbots/llm/__init__.py
microbots/llm/anthropic_api.py
microbots/llm/llm.py
microbots/llm/ollama_local.py
microbots/llm/openai_api.py
microbots/tools/tool.py
microbots/tools/tool_test.ipynb
microbots/tools/tool_definitions/browser-use.yaml
microbots/tools/tool_definitions/cscope.yaml
microbots/tools/tool_definitions/browser-use/browser.py
microbots/utils/logger.py
microbots/utils/network.py
microbots/utils/path.py
microbots-0.0.14.dist-info/licenses/LICENSE
microbots-0.0.14.dist-info/METADATA
microbots-0.0.14.dist-info/WHEEL
microbots-0.0.14.dist-info/top_level.txt
microbots-0.0.14.dist-info/RECORD
