Metadata-Version: 2.4
Name: microbots
Version: 0.0.14
Summary: container-based autonomous agent framework
Author-email: xxx <xxx@example.com>
License: MIT License
Project-URL: Source Repo, https://github.com/microsoft/minions
Project-URL: Issues, https://github.com/microsoft/minions/issues
Keywords: agent,bot,micro
Classifier: Operating System :: OS Independent
Classifier: Intended Audience :: Developers
Classifier: License :: OSI Approved :: MIT License
Classifier: Programming Language :: Python :: 3.11
Requires-Python: >=3.11
License-File: LICENSE
Requires-Dist: openai==1.107.3
Requires-Dist: anthropic==0.75.0
Requires-Dist: python-dotenv==1.1.1
Requires-Dist: docker==7.1.0
Requires-Dist: fastapi==0.116.1
Requires-Dist: uvicorn==0.35.0
Requires-Dist: pydantic==2.11.9
Requires-Dist: swe-rex==1.4.0
Requires-Dist: aiohttp==3.12.15
Requires-Dist: pyyaml==6.0.2
Dynamic: license-file
